Eda/__init__.py
Eda/jay.py
Autoanalysis-1.0.0.dist-info/LICENSE.txt
Autoanalysis-1.0.0.dist-info/METADATA
Autoanalysis-1.0.0.dist-info/WHEEL
Autoanalysis-1.0.0.dist-info/top_level.txt
Autoanalysis-1.0.0.dist-info/RECORD
