Metadata-Version: 2.1
Name: Autoanalysis
Version: 1.0.0
Summary: This package reads automatically the files which have the extensions(excel,csv,pdf) and  perform EDA Anlaysis and produce the graphs.
Home-page: https://github.com/jayavardhana0409
Author: Jayavardhana Reddy Kotla
Author-email: jaireddy1737@gmail.com
Classifier: Programming Language :: Python :: 3
Classifier: License :: OSI Approved :: MIT License
Classifier: Operating System :: OS Independent
Requires-Python: >=3.10
License-File: LICENSE.txt
